dpow/__init__.py
dpow/__main__.py
dpow/client.py
dpow/downloader.py
dpow/server.py
dpow-1.0.1.dist-info/licenses/LICENSE
dpow-1.0.1.dist-info/METADATA
dpow-1.0.1.dist-info/WHEEL
dpow-1.0.1.dist-info/top_level.txt
dpow-1.0.1.dist-info/RECORD
