Metadata-Version: 2.4
Name: dpow
Version: 1.0.1
Summary: Distributed Proof of Work library customized for QudsLab
Author: QudsLab
Classifier: Programming Language :: Python :: 3
Classifier: Operating System :: OS Independent
Requires-Python: >=3.6
License-File: LICENSE
Requires-Dist: requests
Dynamic: author
Dynamic: classifier
Dynamic: license-file
Dynamic: requires-dist
Dynamic: requires-python
Dynamic: summary
